chembl_downloader/contrib.py
chembl_downloader/__init__.py
chembl_downloader/api.py
chembl_downloader/cli.py
chembl_downloader/py.typed
chembl_downloader/queries.py
chembl_downloader/__main__.py
chembl_downloader-0.5.1.dist-info/licenses/LICENSE
chembl_downloader-0.5.1.dist-info/WHEEL
chembl_downloader-0.5.1.dist-info/entry_points.txt
chembl_downloader-0.5.1.dist-info/METADATA
chembl_downloader-0.5.1.dist-info/RECORD
