Metadata-Version: 2.4
Name: chembl-downloader
Version: 0.5.1
Summary: Reproducibly download, open, parse, and query ChEMBL
Keywords: snekpack,cookiecutter,ChEMBL,sqlite,fingerprints
Author: Charles Tapley Hoyt
Author-email: Charles Tapley Hoyt <cthoyt@gmail.com>
License-File: LICENSE
Classifier: Development Status :: 4 - Beta
Classifier: Environment :: Console
Classifier: Intended Audience :: Developers
Classifier: Intended Audience :: Science/Research
Classifier: License :: OSI Approved :: MIT License
Classifier: Operating System :: OS Independent
Classifier: Framework :: Pytest
Classifier: Framework :: tox
Classifier: Framework :: Sphinx
Classifier: Natural Language :: English
Classifier: Programming Language :: Python
Classifier: Programming Language :: Python :: 3.10
Classifier: Programming Language :: Python :: 3.11
Classifier: Programming Language :: Python :: 3.12
Classifier: Programming Language :: Python :: 3.13
Classifier: Programming Language :: Python :: 3 :: Only
Classifier: Typing :: Typed
Classifier: Topic :: Scientific/Engineering :: Chemistry
Requires-Dist: tqdm
Requires-Dist: click
Requires-Dist: more-click
Requires-Dist: pystow
Requires-Dist: typing-extensions
Requires-Dist: sphinx>=8 ; extra == 'docs'
Requires-Dist: sphinx-rtd-theme>=3.0 ; extra == 'docs'
Requires-Dist: sphinx-click ; extra == 'docs'
Requires-Dist: sphinx-automodapi ; extra == 'docs'
Requires-Dist: pandas ; extra == 'pandas'
Requires-Dist: rdkit-pypi ; extra == 'rdkit'
Requires-Dist: pytest ; extra == 'tests'
Requires-Dist: coverage[toml] ; extra == 'tests'
Maintainer: Charles Tapley Hoyt
Maintainer-email: Charles Tapley Hoyt <cthoyt@gmail.com>
Requires-Python: >=3.10
Project-URL: Bug Tracker, https://github.com/cthoyt/chembl-downloader/issues
Project-URL: Documentation, https://chembl_downloader.readthedocs.io
Project-URL: Funding, https://github.com/sponsors/cthoyt
Project-URL: Homepage, https://github.com/cthoyt/chembl-downloader
Project-URL: Repository, https://github.com/cthoyt/chembl-downloader.git
Provides-Extra: docs
Provides-Extra: pandas
Provides-Extra: rdkit
Provides-Extra: tests
